{
  "$schema": "https://raw.githubusercontent.com/spdx/spdx-spec/v2.2.1/schemas/spdx-schema.json",
  "spdxVersion": "SPDX-2.2",
  "dataLicense": "CC0-1.0",
  "SPDXID": "SPDXRef-DOCUMENT",
  "documentNamespace": "https://spdx.org/spdxdocs/opus-x64-windows-1.5.2-baa78b7f-6377-4633-a9f1-deed0b378829",
  "name": "opus:x64-windows@1.5.2 5b94b5403cb281e3a3170054de9ed313f486015547a94c6a961932f56dacd434",
  "creationInfo": {
    "creators": [
      "Tool: vcpkg-2025-09-03-4580816534ed8fd9634ac83d46471440edd82dfe"
    ],
    "created": "2025-10-17T06:58:29Z"
  },
  "relationships": [
    {
      "spdxElementId": "SPDXRef-port",
      "relationshipType": "GENERATES",
      "relatedSpdxElement": "SPDXRef-binary"
    },
    {
      "spdxElementId": "SPDXRef-port",
      "relationshipType": "CONTAINS",
      "relatedSpdxElement": "SPDXRef-port-file-0"
    },
    {
      "spdxElementId": "SPDXRef-port",
      "relationshipType": "CONTAINS",
      "relatedSpdxElement": "SPDXRef-port-file-1"
    },
    {
      "spdxElementId": "SPDXRef-port",
      "relationshipType": "CONTAINS",
      "relatedSpdxElement": "SPDXRef-port-file-2"
    },
    {
      "spdxElementId": "SPDXRef-port-file-2",
      "relationshipType": "DEPENDENCY_MANIFEST_OF",
      "relatedSpdxElement": "SPDXRef-port"
    },
    {
      "spdxElementId": "SPDXRef-binary",
      "relationshipType": "CONTAINS",
      "relatedSpdxElement": "SPDXRef-binary-file-0"
    },
    {
      "spdxElementId": "SPDXRef-binary",
      "relationshipType": "CONTAINS",
      "relatedSpdxElement": "SPDXRef-binary-file-1"
    },
    {
      "spdxElementId": "SPDXRef-binary",
      "relationshipType": "CONTAINS",
      "relatedSpdxElement": "SPDXRef-binary-file-2"
    },
    {
      "spdxElementId": "SPDXRef-binary",
      "relationshipType": "CONTAINS",
      "relatedSpdxElement": "SPDXRef-binary-file-3"
    },
    {
      "spdxElementId": "SPDXRef-binary",
      "relationshipType": "CONTAINS",
      "relatedSpdxElement": "SPDXRef-binary-file-4"
    },
    {
      "spdxElementId": "SPDXRef-binary",
      "relationshipType": "CONTAINS",
      "relatedSpdxElement": "SPDXRef-binary-file-5"
    },
    {
      "spdxElementId": "SPDXRef-binary",
      "relationshipType": "CONTAINS",
      "relatedSpdxElement": "SPDXRef-binary-file-6"
    },
    {
      "spdxElementId": "SPDXRef-binary",
      "relationshipType": "CONTAINS",
      "relatedSpdxElement": "SPDXRef-binary-file-7"
    },
    {
      "spdxElementId": "SPDXRef-binary",
      "relationshipType": "CONTAINS",
      "relatedSpdxElement": "SPDXRef-binary-file-8"
    },
    {
      "spdxElementId": "SPDXRef-binary",
      "relationshipType": "CONTAINS",
      "relatedSpdxElement": "SPDXRef-binary-file-9"
    },
    {
      "spdxElementId": "SPDXRef-binary",
      "relationshipType": "CONTAINS",
      "relatedSpdxElement": "SPDXRef-binary-file-10"
    },
    {
      "spdxElementId": "SPDXRef-binary",
      "relationshipType": "CONTAINS",
      "relatedSpdxElement": "SPDXRef-binary-file-11"
    },
    {
      "spdxElementId": "SPDXRef-binary",
      "relationshipType": "CONTAINS",
      "relatedSpdxElement": "SPDXRef-binary-file-12"
    },
    {
      "spdxElementId": "SPDXRef-binary",
      "relationshipType": "CONTAINS",
      "relatedSpdxElement": "SPDXRef-binary-file-13"
    },
    {
      "spdxElementId": "SPDXRef-binary",
      "relationshipType": "CONTAINS",
      "relatedSpdxElement": "SPDXRef-binary-file-14"
    },
    {
      "spdxElementId": "SPDXRef-binary",
      "relationshipType": "CONTAINS",
      "relatedSpdxElement": "SPDXRef-binary-file-15"
    },
    {
      "spdxElementId": "SPDXRef-binary",
      "relationshipType": "CONTAINS",
      "relatedSpdxElement": "SPDXRef-binary-file-16"
    },
    {
      "spdxElementId": "SPDXRef-binary",
      "relationshipType": "CONTAINS",
      "relatedSpdxElement": "SPDXRef-binary-file-17"
    },
    {
      "spdxElementId": "SPDXRef-binary",
      "relationshipType": "CONTAINS",
      "relatedSpdxElement": "SPDXRef-binary-file-18"
    },
    {
      "spdxElementId": "SPDXRef-binary",
      "relationshipType": "CONTAINS",
      "relatedSpdxElement": "SPDXRef-binary-file-19"
    }
  ],
  "packages": [
    {
      "name": "opus",
      "SPDXID": "SPDXRef-port",
      "versionInfo": "1.5.2",
      "downloadLocation": "git+https://github.com/Microsoft/vcpkg#ports/opus",
      "homepage": "https://github.com/xiph/opus",
      "licenseConcluded": "BSD-3-Clause",
      "licenseDeclared": "NOASSERTION",
      "copyrightText": "NOASSERTION",
      "description": "Totally open, royalty-free, highly versatile audio codec",
      "comment": "This is the port (recipe) consumed by vcpkg."
    },
    {
      "name": "opus:x64-windows",
      "SPDXID": "SPDXRef-binary",
      "versionInfo": "5b94b5403cb281e3a3170054de9ed313f486015547a94c6a961932f56dacd434",
      "downloadLocation": "NONE",
      "licenseConcluded": "BSD-3-Clause",
      "licenseDeclared": "NOASSERTION",
      "copyrightText": "NOASSERTION",
      "comment": "This is a binary package built by vcpkg."
    },
    {
      "SPDXID": "SPDXRef-resource-0",
      "name": "xiph/opus",
      "downloadLocation": "git+https://github.com/xiph/opus@v1.5.2",
      "licenseConcluded": "NOASSERTION",
      "licenseDeclared": "NOASSERTION",
      "copyrightText": "NOASSERTION",
      "checksums": [
        {
          "algorithm": "SHA512",
          "checksumValue": "4ffefd9c035671024f9720c5129bfe395dea04f0d6b730041c2804e89b1db6e4d19633ad1ae58855afc355034233537361e707f26dc53adac916554830038fab"
        }
      ]
    }
  ],
  "files": [
    {
      "fileName": "./fix-pkgconfig-version.patch",
      "SPDXID": "SPDXRef-port-file-0",
      "checksums": [
        {
          "algorithm": "SHA256",
          "checksumValue": "b1998186940daff04e5c332fbb7f27f756cf5c2227f6e8c3f37f2fb2e8222286"
        }
      ],
      "licenseConcluded": "NOASSERTION",
      "copyrightText": "NOASSERTION"
    },
    {
      "fileName": "./portfile.cmake",
      "SPDXID": "SPDXRef-port-file-1",
      "checksums": [
        {
          "algorithm": "SHA256",
          "checksumValue": "ae5184241049d4134b91b67a747d54e2084ea7fe9f170136d4a59fc02c99167d"
        }
      ],
      "licenseConcluded": "NOASSERTION",
      "copyrightText": "NOASSERTION"
    },
    {
      "fileName": "./vcpkg.json",
      "SPDXID": "SPDXRef-port-file-2",
      "checksums": [
        {
          "algorithm": "SHA256",
          "checksumValue": "024bb3bdbf503bebb3033149127cff008e83de347efb17534ece30dfa2f10690"
        }
      ],
      "licenseConcluded": "NOASSERTION",
      "copyrightText": "NOASSERTION"
    },
    {
      "fileName": "./bin/opus.dll",
      "SPDXID": "SPDXRef-binary-file-0",
      "checksums": [
        {
          "algorithm": "SHA256",
          "checksumValue": "fe6f2847f5ba56f0e196991f484b86aa0e28afd523b4b10c850148d1549fedfb"
        }
      ],
      "licenseConcluded": "NOASSERTION",
      "copyrightText": "NOASSERTION"
    },
    {
      "fileName": "./bin/opus.pdb",
      "SPDXID": "SPDXRef-binary-file-1",
      "checksums": [
        {
          "algorithm": "SHA256",
          "checksumValue": "a3dbe3bb49ecbf3b69edb718ce3902988445c3362fbc478f88ab5b914cdc8c4b"
        }
      ],
      "licenseConcluded": "NOASSERTION",
      "copyrightText": "NOASSERTION"
    },
    {
      "fileName": "./BUILD_INFO",
      "SPDXID": "SPDXRef-binary-file-2",
      "checksums": [
        {
          "algorithm": "SHA256",
          "checksumValue": "5e7f821ab4eb804deb535baa7b41edca682d0303cf21a91908c98d5c9a7dcf4d"
        }
      ],
      "licenseConcluded": "NOASSERTION",
      "copyrightText": "NOASSERTION"
    },
    {
      "fileName": "./debug/bin/opus.dll",
      "SPDXID": "SPDXRef-binary-file-3",
      "checksums": [
        {
          "algorithm": "SHA256",
          "checksumValue": "0696017d4e5e72027d73b5796e95807c7b7c9c65122ddcd4b499fd476acc82da"
        }
      ],
      "licenseConcluded": "NOASSERTION",
      "copyrightText": "NOASSERTION"
    },
    {
      "fileName": "./debug/bin/opus.pdb",
      "SPDXID": "SPDXRef-binary-file-4",
      "checksums": [
        {
          "algorithm": "SHA256",
          "checksumValue": "2c664afe06a7b012a6a0921af07ce94805dce6a3bdfc49257fef0e0a2457b7b6"
        }
      ],
      "licenseConcluded": "NOASSERTION",
      "copyrightText": "NOASSERTION"
    },
    {
      "fileName": "./debug/lib/opus.lib",
      "SPDXID": "SPDXRef-binary-file-5",
      "checksums": [
        {
          "algorithm": "SHA256",
          "checksumValue": "998c64a2c846ffd801ea434a297a9ff41f881861c03e468ae8170fc005c5aa52"
        }
      ],
      "licenseConcluded": "NOASSERTION",
      "copyrightText": "NOASSERTION"
    },
    {
      "fileName": "./debug/lib/pkgconfig/opus.pc",
      "SPDXID": "SPDXRef-binary-file-6",
      "checksums": [
        {
          "algorithm": "SHA256",
          "checksumValue": "0688a2c408a9e921c9b2c96fd98c732cf7a93b33a376aa79ccc2e27e1d0b753e"
        }
      ],
      "licenseConcluded": "NOASSERTION",
      "copyrightText": "NOASSERTION"
    },
    {
      "fileName": "./include/opus/opus.h",
      "SPDXID": "SPDXRef-binary-file-7",
      "checksums": [
        {
          "algorithm": "SHA256",
          "checksumValue": "0d5e90fe5d2651ce616b238a81b33d393949b99ef9528efdbd653c0097abbbd4"
        }
      ],
      "licenseConcluded": "NOASSERTION",
      "copyrightText": "NOASSERTION"
    },
    {
      "fileName": "./include/opus/opus_defines.h",
      "SPDXID": "SPDXRef-binary-file-8",
      "checksums": [
        {
          "algorithm": "SHA256",
          "checksumValue": "8918f65309058be1921e59e9ef9cd4081497ce8a487e55cb45c5547046447d9b"
        }
      ],
      "licenseConcluded": "NOASSERTION",
      "copyrightText": "NOASSERTION"
    },
    {
      "fileName": "./include/opus/opus_multistream.h",
      "SPDXID": "SPDXRef-binary-file-9",
      "checksums": [
        {
          "algorithm": "SHA256",
          "checksumValue": "49b727edb7306f94980713bb6c2777fa1fb52de00005cd77c5aff3b935435c22"
        }
      ],
      "licenseConcluded": "NOASSERTION",
      "copyrightText": "NOASSERTION"
    },
    {
      "fileName": "./include/opus/opus_projection.h",
      "SPDXID": "SPDXRef-binary-file-10",
      "checksums": [
        {
          "algorithm": "SHA256",
          "checksumValue": "a53752449f55b5f60679eab8fda96835102251aeefccf7c54256460d02747216"
        }
      ],
      "licenseConcluded": "NOASSERTION",
      "copyrightText": "NOASSERTION"
    },
    {
      "fileName": "./include/opus/opus_types.h",
      "SPDXID": "SPDXRef-binary-file-11",
      "checksums": [
        {
          "algorithm": "SHA256",
          "checksumValue": "19cb301ea1eedbcbdbb5049363de061893bf11c20e505a657b69ce6ffa5b11fa"
        }
      ],
      "licenseConcluded": "NOASSERTION",
      "copyrightText": "NOASSERTION"
    },
    {
      "fileName": "./lib/opus.lib",
      "SPDXID": "SPDXRef-binary-file-12",
      "checksums": [
        {
          "algorithm": "SHA256",
          "checksumValue": "998c64a2c846ffd801ea434a297a9ff41f881861c03e468ae8170fc005c5aa52"
        }
      ],
      "licenseConcluded": "NOASSERTION",
      "copyrightText": "NOASSERTION"
    },
    {
      "fileName": "./lib/pkgconfig/opus.pc",
      "SPDXID": "SPDXRef-binary-file-13",
      "checksums": [
        {
          "algorithm": "SHA256",
          "checksumValue": "4716f6807cdc30881045f29efb90a300d246a3b7c2d8e5c374375a34fd2590be"
        }
      ],
      "licenseConcluded": "NOASSERTION",
      "copyrightText": "NOASSERTION"
    },
    {
      "fileName": "./share/opus/copyright",
      "SPDXID": "SPDXRef-binary-file-14",
      "checksums": [
        {
          "algorithm": "SHA256",
          "checksumValue": "01e1167d54a096d123cf6dfbbeb19587278845c6481d2d66d545669846079551"
        }
      ],
      "licenseConcluded": "NOASSERTION",
      "copyrightText": "NOASSERTION"
    },
    {
      "fileName": "./share/opus/OpusConfig.cmake",
      "SPDXID": "SPDXRef-binary-file-15",
      "checksums": [
        {
          "algorithm": "SHA256",
          "checksumValue": "b24a920347af41ffe18489f7a85ccb2c8da3f0846cce6a48599df0644c1aeb1f"
        }
      ],
      "licenseConcluded": "NOASSERTION",
      "copyrightText": "NOASSERTION"
    },
    {
      "fileName": "./share/opus/OpusConfigVersion.cmake",
      "SPDXID": "SPDXRef-binary-file-16",
      "checksums": [
        {
          "algorithm": "SHA256",
          "checksumValue": "4a630aec38d10eeba504cfee8c6aebee2e7b44500371fc39985262a6de1ff52c"
        }
      ],
      "licenseConcluded": "NOASSERTION",
      "copyrightText": "NOASSERTION"
    },
    {
      "fileName": "./share/opus/OpusTargets-debug.cmake",
      "SPDXID": "SPDXRef-binary-file-17",
      "checksums": [
        {
          "algorithm": "SHA256",
          "checksumValue": "09b805042e801018171adbf1103b30bdd6f058177dd87e3958e055ff128db9bf"
        }
      ],
      "licenseConcluded": "NOASSERTION",
      "copyrightText": "NOASSERTION"
    },
    {
      "fileName": "./share/opus/OpusTargets-release.cmake",
      "SPDXID": "SPDXRef-binary-file-18",
      "checksums": [
        {
          "algorithm": "SHA256",
          "checksumValue": "536bd36fb9cdb7e5c485b727996117fa74ec2648cac3f098c49de7bd6eb888e0"
        }
      ],
      "licenseConcluded": "NOASSERTION",
      "copyrightText": "NOASSERTION"
    },
    {
      "fileName": "./share/opus/OpusTargets.cmake",
      "SPDXID": "SPDXRef-binary-file-19",
      "checksums": [
        {
          "algorithm": "SHA256",
          "checksumValue": "6ccaf587b2de536866c6a7c733f372ef96b20b68c1a76bc42f751c949531e863"
        }
      ],
      "licenseConcluded": "NOASSERTION",
      "copyrightText": "NOASSERTION"
    }
  ]
}
